lesscpy/__init__.py
lesscpy/__main__.py
lesscpy/exceptions.py
lesscpy/lessc/__init__.py
lesscpy/lessc/color.py
lesscpy/lessc/formatter.py
lesscpy/lessc/lexer.py
lesscpy/lessc/parser.py
lesscpy/lessc/scope.py
lesscpy/lessc/utility.py
lesscpy/lib/__init__.py
lesscpy/lib/colors.py
lesscpy/lib/css.py
lesscpy/lib/dom.py
lesscpy/lib/reserved.py
lesscpy/plib/__init__.py
lesscpy/plib/block.py
lesscpy/plib/call.py
lesscpy/plib/deferred.py
lesscpy/plib/expression.py
lesscpy/plib/identifier.py
lesscpy/plib/import_.py
lesscpy/plib/keyframe_selector.py
lesscpy/plib/mixin.py
lesscpy/plib/negated_expression.py
lesscpy/plib/node.py
lesscpy/plib/property.py
lesscpy/plib/statement.py
lesscpy/plib/variable.py
lesscpy/scripts/__init__.py
lesscpy/scripts/compiler.py
lesscpy-0.15.1.dist-info/AUTHORS
lesscpy-0.15.1.dist-info/LICENSE
lesscpy-0.15.1.dist-info/METADATA
lesscpy-0.15.1.dist-info/WHEEL
lesscpy-0.15.1.dist-info/entry_points.txt
lesscpy-0.15.1.dist-info/top_level.txt
lesscpy-0.15.1.dist-info/RECORD
